{
  "db_name": "PostgreSQL",
  "query": "\n            INSERT INTO api_keys (vessel_id, api_key, expires_at)\n            VALUES ($1, $2, $3)\n            RETURNING id\n            ",
  "describe": {
    "columns": [
      {
        "ordinal": 0,
        "name": "id",
        "type_info": "Int4"
      }
    ],
    "parameters": {
      "Left": [
        "Varchar",
        "Varchar",
        "Timestamptz"
      ]
    },
    "nullable": [
      false
    ]
  },
  "hash": "77fd50c23096ec5590cf70e0071e3ea767f1094d5cec3f810982437fd714ca06"
}
